scrahub/__init__.py
scrahub/cli/__init__.py
scrahub/config/__init__.py
scrahub/constants/__init__.py
scrahub/core/__init__.py
scrahub/core/client.py
scrahub/core/config.py
scrahub/core/log.py
scrahub/core/request.py
scrahub/db/__init__.py
scrahub/db/es.py
scrahub/db/kafka.py
scrahub/db/mongo.py
scrahub/db/sql.py
scrahub/pipelines/__init__.py
scrahub/utils/__init__.py
scrahub/utils/config.py
scrahub/utils/data.py
scrahub/utils/scrapy.py
scrahub_sdk-0.3.3.dist-info/METADATA
scrahub_sdk-0.3.3.dist-info/WHEEL
scrahub_sdk-0.3.3.dist-info/entry_points.txt
scrahub_sdk-0.3.3.dist-info/top_level.txt
scrahub_sdk-0.3.3.dist-info/RECORD
